{"time": ["None", 95.983, "None", 96.219, 122.745, "None", 142.216], "lap": [1.0, 2.0, 3.0, 4.0, 5.0, 6.0, 7.0], "compound": ["SOFT", "SOFT", "SOFT", "SOFT", "SOFT", "SOFT", "SOFT"], "stint": [1, 1, 1, 1, 1, 2, 2], "s1": ["None", 25.908, 58.751, 25.962, 34.398, "None", 28.28], "s2": [57.218, 38.484, 71.917, 38.57, 43.882, 60.702, 58.891], "s3": [50.706, 31.591, 61.046, 31.687, 44.465, 77.06, 55.045], "life": [1, 2, 3, 4, 5, 1, 2], "pos": ["None", "None", "None", "None", "None", "None", "None"], "status": ["1", "1", "1", "1", "1", "1", "12"], "pb": [false, true, false, false, false, false, false]}