{"time": ["None", "None", 115.287, 110.152, 109.364, 108.98, 129.919, "None", 107.982, 146.855, 106.772, 139.396, "None", 112.605, 111.696, 111.857, 113.658, 112.638, "None"], "lap": [1.0, 2.0, 3.0, 4.0, 5.0, 6.0, 7.0, 8.0, 9.0, 10.0, 11.0, 12.0, 13.0, 14.0, 15.0, 16.0, 17.0, 18.0, 19.0], "compound": ["INTERMEDIATE", "MEDIUM", "MEDIUM", "MEDIUM", "MEDIUM", "MEDIUM", "MEDIUM", "SOFT", "SOFT", "SOFT", "SOFT", "SOFT", "MEDIUM", "MEDIUM", "MEDIUM", "MEDIUM", "MEDIUM", "MEDIUM", "MEDIUM"], "stint": [1, 2, 2, 2, 2, 2, 2, 3, 3, 3, 3, 3, 4, 4, 4, 4, 4, 4, 4], "s1": ["None", 55.979, 31.766, 31.811, 31.736, 31.514, 31.628, "None", 31.561, 44.235, 31.139, 44.21, "None", 32.204, 32.125, 31.924, 32.174, 32.05, 39.92], "s2": [86.104, 55.455, 52.575, 47.758, 47.171, 47.216, 58.705, 62.84, 46.324, 66.492, 45.745, 58.267, 50.405, 49.42, 49.289, 49.675, 50.487, 49.756, 68.277], "s3": [52.842, 46.011, 30.946, 30.583, 30.457, 30.25, 39.586, 35.232, 30.097, 36.128, 29.888, 36.919, 30.715, 30.981, 30.282, 30.258, 30.997, 30.832, 50.739], "life": [1, 1, 2, 3, 4, 5, 6, 1, 2, 3, 4, 5, 7, 8, 9, 10, 11, 12, 13], "pos": ["None", "None", "None", "None", "None", "None", "None", "None", "None", "None", "None", "None", "None", "None", "None", "None", "None", "None", "None"], "status": ["12", "12", "1", "1", "1", "1", "1", "1", "1", "1", "1", "12", "12", "12", "1", "1", "1", "1", "1"], "pb": [false, false, true, true, true, true, false, false, true, false, true, false, false, false, false, false, false, false, false]}