{"racePace": [{"Driver": "VER", "LapTime": 100.498, "Diff": 0.0, "Team": "Red Bull Racing"}, {"Driver": "HAM", "LapTime": 100.5, "Diff": 0.002, "Team": "Mercedes"}, {"Driver": "PER", "LapTime": 101.14, "Diff": 0.642, "Team": "Red Bull Racing"}, {"Driver": "LEC", "LapTime": 101.358, "Diff": 0.86, "Team": "Ferrari"}, {"Driver": "BOT", "LapTime": 101.718, "Diff": 1.22, "Team": "Mercedes"}, {"Driver": "SAI", "LapTime": 101.798, "Diff": 1.3, "Team": "Ferrari"}, {"Driver": "RIC", "LapTime": 101.803, "Diff": 1.305, "Team": "McLaren"}, {"Driver": "NOR", "LapTime": 101.898, "Diff": 1.4, "Team": "McLaren"}, {"Driver": "ALO", "LapTime": 102.469, "Diff": 1.971, "Team": "Alpine"}, {"Driver": "VET", "LapTime": 102.672, "Diff": 2.174, "Team": "Aston Martin"}, {"Driver": "TSU", "LapTime": 102.757, "Diff": 2.259, "Team": "AlphaTauri"}, {"Driver": "RAI", "LapTime": 102.831, "Diff": 2.333, "Team": "Alfa Romeo Racing"}, {"Driver": "GIO", "LapTime": 102.913, "Diff": 2.415, "Team": "Alfa Romeo Racing"}, {"Driver": "STR", "LapTime": 103.083, "Diff": 2.585, "Team": "Aston Martin"}, {"Driver": "RUS", "LapTime": 103.231, "Diff": 2.733, "Team": "Williams"}, {"Driver": "LAT", "LapTime": 103.504, "Diff": 3.006, "Team": "Williams"}, {"Driver": "OCO", "LapTime": 103.619, "Diff": 3.121, "Team": "Alpine"}, {"Driver": "MSC", "LapTime": 103.64, "Diff": 3.142, "Team": "Haas F1 Team"}, {"Driver": "GAS", "LapTime": 103.813, "Diff": 3.315, "Team": "AlphaTauri"}, {"Driver": "MAZ", "LapTime": 103.9, "Diff": 3.402, "Team": "Haas F1 Team"}]}