{"time": ["None", 70.148, 107.959, 98.765, 69.97, 86.806, "None", 69.451, 90.519, "None", 69.486, 91.597, "None", 69.399, 98.733], "lap": [1.0, 2.0, 3.0, 4.0, 5.0, 6.0, 7.0, 8.0, 9.0, 10.0, 11.0, 12.0, 13.0, 14.0, 15.0], "compound": ["SOFT", "SOFT", "SOFT", "SOFT", "SOFT", "SOFT", "SOFT", "SOFT", "SOFT", "SOFT", "SOFT", "SOFT", "SOFT", "SOFT", "SOFT"], "stint": [1, 1, 1, 1, 1, 1, 2, 2, 2, 3, 3, 3, 4, 4, 4], "s1": ["None", 18.1, 25.664, 24.483, 18.117, 21.989, "None", 17.949, 22.339, "None", 17.998, 22.108, "None", 17.834, 26.1], "s2": [51.27, 35.668, 58.335, 55.765, 35.529, 42.644, 55.596, 35.27, 43.37, 61.877, 35.239, 44.697, 54.6, 35.238, 46.181], "s3": [17.764, 16.38, 23.96, 18.517, 16.324, 22.173, 19.413, 16.232, 24.81, 17.938, 16.249, 24.792, 18.393, 16.327, 26.452], "life": [1, 2, 3, 4, 5, 6, 1, 2, 3, 1, 2, 3, 1, 2, 3], "pos": ["None", "None", "None", "None", "None", "None", "None", "None", "None", "None", "None", "None", "None", "None", "None"], "status": ["1", "1", "1", "1", "1", "1", "1", "1", "1", "1", "1", "1", "1", "1", "1"], "pb": [false, true, false, false, true, false, false, true, false, false, true, false, false, true, false]}