{"time": ["None", 132.31, 128.517, 142.885, "None", 121.646, 119.87, 134.723, "None", 147.899, 131.58, 118.767, 132.543, "None", 116.295, 150.636, "None", "None", 123.093, "None", 122.502, "None"], "lap": [1.0, 2.0, 3.0, 4.0, 5.0, 6.0, 7.0, 8.0, 9.0, 10.0, 11.0, 12.0, 13.0, 14.0, 15.0, 16.0, 17.0, 18.0, 19.0, 20.0, 21.0, 22.0], "compound": ["WET", "WET", "WET", "WET", "INTERMEDIATE", "INTERMEDIATE", "INTERMEDIATE", "INTERMEDIATE", "INTERMEDIATE", "INTERMEDIATE", "INTERMEDIATE", "INTERMEDIATE", "INTERMEDIATE", "INTERMEDIATE", "INTERMEDIATE", "INTERMEDIATE", "WET", "INTERMEDIATE", "INTERMEDIATE", "INTERMEDIATE", "INTERMEDIATE", "INTERMEDIATE"], "stint": [1, 1, 1, 1, 2, 2, 2, 2, 3, 4, 4, 4, 4, 5, 5, 5, 6, 7, 7, 7, 7, 7], "s1": ["None", 35.53, 34.975, 36.598, 65.997, 33.629, 33.231, 33.223, "None", 54.027, 32.957, 32.814, 33.202, 49.507, 32.39, 35.911, "None", "None", 34.313, 37.091, 34.28, 42.185], "s2": [70.12, 62.677, 59.951, 63.096, 61.84, 56.004, 55.008, 59.088, 62.565, 58.688, 58.659, 54.581, 60.676, 60.619, 52.764, 67.22, "None", 63.54, 56.995, 65.896, 55.917, 64.058], "s3": [72.41, 34.103, 33.591, 43.191, 35.372, 32.013, 31.631, 42.412, 46.367, 35.184, 39.964, 31.372, 38.665, 53.27, 31.141, 47.505, "None", 41.085, 31.785, 58.902, 32.305, "None"], "life": [1, 2, 3, 4, 1, 2, 3, 4, 5, 1, 2, 3, 4, 1, 2, 3, 1, 1, 2, 3, 4, 5], "pos": ["None", "None", "None", "None", "None", "None", "None", "None", "None", "None", "None", "None", "None", "None", "None", "None", "None", "None", "None", "None", "None", "None"], "status": ["1", "12", "1", "1", "1", "1", "1", "1", "1", "1", "1", "1", "1", "1", "1", "1", "125", "1", "1", "1", "1", "1"], "pb": [false, true, true, false, false, true, true, false, false, false, true, true, false, false, true, false, false, false, true, false, true, false]}