{"time": ["None", "None", "None", 102.787, 77.491, 102.115, 77.065, 102.24, 80.716, 101.689, 93.46, 127.632, "None", 76.44, 99.93, 76.254, 105.511, 76.23, 103.617, 117.443], "lap": [1.0, 2.0, 3.0, 4.0, 5.0, 6.0, 7.0, 8.0, 9.0, 10.0, 11.0, 12.0, 13.0, 14.0, 15.0, 16.0, 17.0, 18.0, 19.0, 20.0], "compound": ["MEDIUM", "MEDIUM", "MEDIUM", "MEDIUM", "MEDIUM", "MEDIUM", "MEDIUM", "MEDIUM", "MEDIUM", "MEDIUM", "MEDIUM", "MEDIUM", "SOFT", "SOFT", "SOFT", "SOFT", "SOFT", "SOFT", "SOFT", "SOFT"], "stint": [1, 1, 2, 2, 2, 2, 2, 2, 2, 2, 2, 3, 4, 4, 4, 4, 4, 4, 4, 4], "s1": ["None", 25.204, "None", 39.119, 24.817, 32.622, 24.552, 32.299, 24.191, 37.221, 24.487, 56.185, "None", 24.342, 30.723, 24.267, 32.153, 24.382, 34.708, 53.438], "s2": [32.573, "None", 29.56, 32.02, 26.675, 37.154, 26.723, 36.765, 26.272, 35.467, 26.364, 36.448, 33.819, 26.575, 36.376, 26.419, 38.839, 26.297, 33.277, 31.088], "s3": [32.383, "None", 30.33, 31.648, 25.999, 32.339, 25.79, 33.176, 30.253, 29.001, 42.609, 34.999, 29.234, 25.523, 32.831, 25.568, 34.519, 25.551, 35.632, 32.917], "life": [1, 2, 3, 4, 5, 6, 7, 8, 9, 10, 11, 12, 1, 2, 3, 4, 5, 6, 7, 8], "pos": ["None", "None", "None", "None", "None", "None", "None", "None", "None", "None", "None", "None", "None", "None", "None", "None", "None", "None", "None", "None"], "status": ["1", "25", "1", "1", "1", "1", "1", "1", "1", "1", "1", "1", "2", "1", "2", "1", "1", "1", "1", "1"], "pb": [false, false, false, true, true, true, true, false, false, false, false, false, false, true, false, true, false, true, false, false]}