{"time": ["None", 99.291, 94.945, 144.208, 94.743, 140.179, 92.461, 134.904, 91.929, 100.631, 139.536, "None", 91.672, 140.092, 104.912, 147.988, 91.036, "None", 90.318, 115.914, "None", 95.617, 96.325, 95.259, 95.231, 120.355, 140.428], "lap": [1.0, 2.0, 3.0, 4.0, 5.0, 6.0, 7.0, 8.0, 9.0, 10.0, 11.0, 12.0, 13.0, 14.0, 15.0, 16.0, 17.0, 18.0, 19.0, 20.0, 21.0, 22.0, 23.0, 24.0, 25.0, 26.0, 27.0], "compound": ["MEDIUM", "MEDIUM", "MEDIUM", "MEDIUM", "MEDIUM", "MEDIUM", "MEDIUM", "MEDIUM", "MEDIUM", "MEDIUM", "MEDIUM", "SOFT", "SOFT", "SOFT", "SOFT", "SOFT", "SOFT", "SOFT", "SOFT", "SOFT", "MEDIUM", "MEDIUM", "MEDIUM", "MEDIUM", "MEDIUM", "MEDIUM", "MEDIUM"], "stint": [1, 1, 1, 1, 1, 1, 1, 1, 1, 1, 2, 3, 3, 3, 3, 3, 3, 3, 3, 3, 4, 4, 4, 4, 4, 4, 4], "s1": ["None", 36.445, 35.319, 55.2, 34.169, 53.387, 33.827, 50.994, 33.662, 34.739, 61.518, "None", 33.543, 53.926, 33.265, 56.957, 33.206, 55.777, 32.962, 42.202, "None", 35.067, 35.892, 34.808, 34.848, 43.45, 67.477], "s2": [38.946, 32.515, 30.035, 47.139, 29.392, 48.017, 29.374, 47.101, 29.143, 29.801, 40.754, 44.772, 29.227, 47.558, 29.189, 50.8, 29.089, 63.867, 28.879, 34.94, 36.211, 30.212, 30.345, 30.24, 30.271, 33.441, 33.44], "s3": [39.549, 30.331, 29.591, 41.869, 31.182, 38.775, 29.26, 36.809, 29.124, 36.091, 37.264, 38.415, 28.902, 38.608, 42.458, 40.231, 28.741, 43.507, 28.477, 38.772, 34.703, 30.338, 30.088, 30.211, 30.112, 43.464, 39.511], "life": [1, 2, 3, 4, 5, 6, 7, 8, 9, 10, 11, 1, 2, 3, 4, 5, 6, 7, 8, 9, 12, 13, 14, 15, 16, 17, 18], "pos": ["None", "None", "None", "None", "None", "None", "None", "None", "None", "None", "None", "None", "None", "None", "None", "None", "None", "None", "None", "None", "None", "None", "None", "None", "None", "None", "None"], "status": ["1", "1", "1", "1", "1", "1", "1", "1", "1", "1", "1", "1", "1", "1", "1", "12", "1", "1", "1", "1", "1", "12", "1", "1", "1", "1", "1"], "pb": [false, true, true, false, true, false, true, false, true, false, false, false, true, false, false, false, true, false, true, false, false, false, false, false, false, false, false]}