{"time": ["None", "None", 97.856, 133.394, 107.745, 135.153, 97.458, 116.782, 98.729, "None", 96.22, "None", 99.743, "None", 102.234, 103.122, 104.673, 104.076], "lap": [1.0, 2.0, 3.0, 4.0, 5.0, 6.0, 7.0, 8.0, 9.0, 10.0, 11.0, 12.0, 13.0, 14.0, 15.0, 16.0, 17.0, 18.0], "compound": ["MEDIUM", "MEDIUM", "MEDIUM", "MEDIUM", "MEDIUM", "MEDIUM", "MEDIUM", "MEDIUM", "MEDIUM", "SOFT", "SOFT", "SOFT", "SOFT", "MEDIUM", "MEDIUM", "MEDIUM", "MEDIUM", "MEDIUM"], "stint": [1, 2, 2, 2, 2, 2, 2, 2, 2, 3, 3, 3, 3, 4, 4, 4, 4, 4], "s1": ["None", "None", 26.036, 38.955, 26.064, 37.018, 25.993, 28.552, 25.86, "None", 25.669, 35.114, 25.89, "None", 27.091, 27.192, 27.505, 27.754], "s2": [46.794, 44.475, 39.112, 55.284, 39.731, 52.079, 39.101, 49.108, 39.165, 59.05, 38.497, 65.021, 39.464, 42.031, 41.419, 41.358, 42.647, 41.973], "s3": ["None", 43.342, 32.708, 39.155, 41.95, 46.056, 32.364, 39.122, 33.704, 49.14, 32.054, 52.871, 34.389, 34.446, 33.724, 34.572, 34.521, 34.349], "life": [1, 2, 3, 4, 5, 6, 7, 8, 9, 1, 2, 3, 4, 10, 11, 12, 13, 14], "pos": ["None", "None", "None", "None", "None", "None", "None", "None", "None", "None", "None", "None", "None", "None", "None", "None", "None", "None"], "status": ["125", "1", "1", "1", "12", "21", "1", "1", "1", "12", "21", "1", "1", "1", "1", "12", "12", "1"], "pb": [false, false, true, true, true, false, true, false, false, false, false, false, false, false, false, false, false, false]}