{"time": ["None", 102.862, 143.618, 100.724, "None", 100.531, 134.131, "None", 118.492, 139.845, 98.586, "None", 133.229, "None", 104.975, 104.412, 103.901, 104.371, 104.533, 104.263, 104.712, 129.648], "lap": [1.0, 2.0, 3.0, 4.0, 5.0, 6.0, 7.0, 8.0, 9.0, 10.0, 11.0, 12.0, 13.0, 14.0, 15.0, 16.0, 17.0, 18.0, 19.0, 20.0, 21.0, 22.0], "compound": ["MEDIUM", "MEDIUM", "MEDIUM", "MEDIUM", "MEDIUM", "MEDIUM", "MEDIUM", "SOFT", "SOFT", "SOFT", "SOFT", "SOFT", "SOFT", "MEDIUM", "MEDIUM", "MEDIUM", "MEDIUM", "MEDIUM", "MEDIUM", "MEDIUM", "MEDIUM", "MEDIUM"], "stint": [1, 1, 1, 1, 1, 1, 1, 2, 2, 2, 2, 2, 2, 3, 3, 3, 3, 3, 3, 3, 3, 3], "s1": ["None", 37.357, 44.57, 36.318, 50.589, 36.417, 49.346, "None", 35.783, 51.547, 35.809, 58.85, 40.081, "None", 38.104, 37.602, 37.498, 37.563, 37.459, 37.691, 37.637, 44.813], "s2": [43.162, 35.238, 57.178, 34.291, 55.796, 34.144, 43.641, 49.581, 40.771, 49.728, 33.592, 56.901, 52.093, 39.11, 36.023, 35.818, 35.692, 35.834, 36.037, 35.893, 36.163, 45.111], "s3": [40.175, 30.267, 41.87, 30.115, 44.301, 29.97, 41.144, 37.188, 41.938, 38.57, 29.185, 39.47, 41.055, 33.684, 30.848, 30.992, 30.711, 30.974, 31.037, 30.679, 30.912, 39.724], "life": [1, 2, 3, 4, 5, 6, 7, 1, 2, 3, 4, 5, 6, 8, 9, 10, 11, 12, 13, 14, 15, 16], "pos": ["None", "None", "None", "None", "None", "None", "None", "None", "None", "None", "None", "None", "None", "None", "None", "None", "None", "None", "None", "None", "None", "None"], "status": ["1", "1", "1", "1", "1", "1", "1", "1", "1", "1", "1", "1", "167", "1", "1", "1", "1", "1", "1", "1", "1", "1"], "pb": [false, true, false, true, false, true, false, false, false, false, true, false, false, false, false, false, false, false, false, false, false, false]}