{"racePace": [{"Driver": "HAM", "LapTime": 73.595, "Diff": 0.0, "Team": "Mercedes"}, {"Driver": "VER", "LapTime": 73.776, "Diff": 0.181, "Team": "Red Bull Racing"}, {"Driver": "PER", "LapTime": 73.821, "Diff": 0.226, "Team": "Red Bull Racing"}, {"Driver": "BOT", "LapTime": 73.874, "Diff": 0.279, "Team": "Mercedes"}, {"Driver": "SAI", "LapTime": 74.307, "Diff": 0.712, "Team": "Ferrari"}, {"Driver": "LEC", "LapTime": 74.356, "Diff": 0.761, "Team": "Ferrari"}, {"Driver": "RAI", "LapTime": 74.443, "Diff": 0.848, "Team": "Alfa Romeo Racing"}, {"Driver": "NOR", "LapTime": 74.722, "Diff": 1.127, "Team": "McLaren"}, {"Driver": "GAS", "LapTime": 74.739, "Diff": 1.144, "Team": "AlphaTauri"}, {"Driver": "VET", "LapTime": 74.748, "Diff": 1.153, "Team": "Aston Martin"}, {"Driver": "ALO", "LapTime": 74.919, "Diff": 1.324, "Team": "Alpine"}, {"Driver": "TSU", "LapTime": 74.98, "Diff": 1.385, "Team": "AlphaTauri"}, {"Driver": "RUS", "LapTime": 74.993, "Diff": 1.398, "Team": "Williams"}, {"Driver": "LAT", "LapTime": 75.015, "Diff": 1.42, "Team": "Williams"}, {"Driver": "GIO", "LapTime": 75.105, "Diff": 1.51, "Team": "Alfa Romeo Racing"}, {"Driver": "MSC", "LapTime": 75.122, "Diff": 1.527, "Team": "Haas F1 Team"}, {"Driver": "OCO", "LapTime": 75.123, "Diff": 1.528, "Team": "Alpine"}, {"Driver": "RIC", "LapTime": 75.211, "Diff": 1.616, "Team": "McLaren"}, {"Driver": "STR", "LapTime": 75.573, "Diff": 1.978, "Team": "Aston Martin"}, {"Driver": "MAZ", "LapTime": 75.6, "Diff": 2.005, "Team": "Haas F1 Team"}]}