{"time": [130.106, 97.374, 119.842, 96.024, "None", 119.765, 95.791, 141.584, "None", 123.534, 94.95, "None", 122.181, 94.974, "None", 139.703, 99.468, 99.733, 99.185, 126.525, 123.201, 98.832, 99.277, "None"], "lap": [1.0, 2.0, 3.0, 4.0, 5.0, 6.0, 7.0, 8.0, 9.0, 10.0, 11.0, 12.0, 13.0, 14.0, 15.0, 16.0, 17.0, 18.0, 19.0, 20.0, 21.0, 22.0, 23.0, 24.0], "compound": ["MEDIUM", "MEDIUM", "MEDIUM", "MEDIUM", "MEDIUM", "MEDIUM", "MEDIUM", "MEDIUM", "MEDIUM", "SOFT", "SOFT", "SOFT", "SOFT", "SOFT", "SOFT", "SOFT", "SOFT", "SOFT", "SOFT", "SOFT", "MEDIUM", "MEDIUM", "MEDIUM", "MEDIUM"], "stint": [1, 1, 1, 1, 1, 2, 2, 2, 3, 4, 4, 4, 4, 4, 4, 5, 5, 5, 5, 5, 6, 6, 6, 6], "s1": [35.208, 24.678, 26.188, 23.99, 35.658, 30.987, 23.788, 31.229, 60.904, 35.25, 23.731, 38.321, 30.724, 23.65, 26.285, 53.425, 25.009, 25.65, 24.871, 25.133, 46.845, 24.813, 24.958, 26.021], "s2": [36.679, 29.695, 36.119, 29.153, 44.035, 32.911, 29.093, 38.477, 29.613, 36.166, 28.656, 47.712, 35.5, 28.618, 32.357, 34.282, 30.338, 29.963, 30.211, 29.977, 30.813, 30.018, 29.812, 30.082], "s3": [58.219, 43.001, 57.535, 42.881, 70.895, 55.867, 42.91, 71.878, "None", 52.118, 42.563, 64.035, 55.957, 42.706, "None", 51.996, 44.121, 44.12, 44.103, 71.415, 45.543, 44.001, 44.507, "None"], "life": [1, 2, 3, 4, 5, 6, 7, 8, 9, 1, 2, 3, 4, 5, 6, 7, 8, 9, 10, 11, 10, 11, 12, 13], "pos": ["None", "None", "None", "None", "None", "None", "None", "None", "None", "None", "None", "None", "None", "None", "None", "None", "None", "None", "None", "None", "None", "None", "None", "None"], "status": ["12", "21", "1", "1", "1", "1", "1", "12", "12", "1", "1", "1", "1", "1", "1", "1", "1", "1", "1", "1", "1", "1", "1", "1"], "pb": [false, true, false, true, false, false, true, false, false, false, true, false, false, false, false, false, false, false, false, false, false, false, false, false]}