{"time": [143.488, 105.58, 122.587, 84.421, 149.242, "None", 83.324, "None", 132.071, 83.154, "None", 140.167, 83.148, "None", "None", 131.048, 92.485, 88.565, 88.238, 88.205, 88.127, 88.303, 88.2, 92.98, 87.685, 87.662, "None"], "lap": [1.0, 2.0, 3.0, 4.0, 5.0, 6.0, 7.0, 8.0, 9.0, 10.0, 11.0, 12.0, 13.0, 14.0, 15.0, 16.0, 17.0, 18.0, 19.0, 20.0, 21.0, 22.0, 23.0, 24.0, 25.0, 26.0, 27.0], "compound": ["MEDIUM", "MEDIUM", "MEDIUM", "MEDIUM", "MEDIUM", "MEDIUM", "MEDIUM", "MEDIUM", "SOFT", "SOFT", "SOFT", "SOFT", "SOFT", "SOFT", "SOFT", "SOFT", "MEDIUM", "MEDIUM", "MEDIUM", "MEDIUM", "MEDIUM", "MEDIUM", "MEDIUM", "MEDIUM", "MEDIUM", "MEDIUM", "MEDIUM"], "stint": [1, 1, 1, 1, 1, 2, 2, 2, 3, 3, 3, 4, 4, 4, 5, 6, 7, 7, 7, 7, 7, 7, 7, 7, 7, 7, 7], "s1": [60.433, 27.919, 39.471, 27.616, 41.425, 83.734, 27.276, 34.1, 48.623, 27.226, 46.442, 65.075, 27.127, 32.245, 62.167, 49.765, 33.401, 28.909, 29.135, 28.947, 28.933, 29.095, 28.975, 29.109, 28.783, 28.791, 28.776], "s2": [39.056, 37.461, 38.001, 28.279, 45.849, 36.637, 28.024, 31.761, 38.21, 27.884, 55.13, 39.723, 27.972, 32.815, 31.456, 29.562, 29.356, 29.987, 29.466, 29.658, 29.55, 29.605, 29.734, 30.142, 29.465, 29.495, 32.445], "s3": [43.999, 40.2, 45.115, 28.526, 61.968, 38.383, 28.024, "None", 45.238, 28.044, 63.977, 35.369, 28.049, "None", 58.912, 51.721, 29.728, 29.669, 29.637, 29.6, 29.644, 29.603, 29.491, 33.729, 29.437, 29.376, "None"], "life": [1, 2, 3, 4, 5, 6, 7, 8, 1, 2, 3, 4, 5, 6, 7, 8, 9, 10, 11, 12, 13, 14, 15, 16, 17, 18, 19], "pos": ["None", "None", "None", "None", "None", "None", "None", "None", "None", "None", "None", "None", "None", "None", "None", "None", "None", "None", "None", "None", "None", "None", "None", "None", "None", "None", "None"], "status": ["1", "1", "1", "1", "1", "1", "1", "1", "1", "1", "1", "1", "1", "1", "12", "1", "1", "1", "1", "1", "1", "1", "1", "1", "1", "1", "1"], "pb": [false, true, false, true, false, false, true, false, false, true, false, false, true, false, false, false, false, false, false, false, false, false, false, false, false, false, false]}