{"time": ["None", 83.266, 113.707, "None", 82.845, 106.646, "None", 83.185, 114.838, "None", 83.145, 105.841, "None", 82.66, 97.752, "None", 82.48, 112.963, "None"], "lap": [1.0, 2.0, 3.0, 4.0, 5.0, 6.0, 7.0, 8.0, 9.0, 10.0, 11.0, 12.0, 13.0, 14.0, 15.0, 16.0, 17.0, 18.0, 19.0], "compound": ["SOFT", "SOFT", "SOFT", "SOFT", "SOFT", "SOFT", "MEDIUM", "MEDIUM", "MEDIUM", "MEDIUM", "MEDIUM", "MEDIUM", "SOFT", "SOFT", "SOFT", "SOFT", "SOFT", "SOFT", "SOFT"], "stint": [1, 1, 1, 2, 2, 2, 3, 3, 3, 4, 4, 4, 5, 5, 5, 6, 6, 6, 6], "s1": ["None", 17.071, 26.719, "None", 16.975, 19.995, "None", 16.924, 29.727, "None", 16.867, 21.964, "None", 16.834, 18.804, "None", 16.902, 23.342, 23.342], "s2": [46.679, 36.03, 46.209, 46.828, 35.788, 46.528, 44.769, 35.847, 45.692, 43.355, 35.973, 43.59, 47.364, 35.866, 40.231, 43.428, 35.783, 46.665, "None"], "s3": [39.069, 30.165, 40.779, 44.612, 30.082, 40.123, 35.432, 30.414, 39.419, 49.423, 30.305, 40.287, 43.645, 29.96, 38.717, 39.103, 29.795, 42.956, "None"], "life": [1, 2, 3, 4, 5, 6, 1, 2, 3, 1, 2, 3, 1, 2, 3, 1, 2, 3, 4], "pos": ["None", "None", "None", "None", "None", "None", "None", "None", "None", "None", "None", "None", "None", "None", "None", "None", "None", "None", "None"], "status": ["1", "1", "1", "1", "1", "1", "12", "1", "1", "12", "12", "1", "12", "1", "1", "1", "1", "1", "1"], "pb": [false, true, false, false, true, false, false, true, false, false, true, false, false, true, false, false, true, false, false]}