{"time": ["None", 97.472, "None", 139.075, 111.051, "None", 96.899, 126.161, "None", 94.874, 144.343, "None", 95.961, 123.789, "None", 100.363, 117.534], "lap": [1.0, 2.0, 3.0, 4.0, 5.0, 6.0, 7.0, 8.0, 9.0, 10.0, 11.0, 12.0, 13.0, 14.0, 15.0, 16.0, 17.0], "compound": ["SOFT", "SOFT", "SOFT", "SOFT", "SOFT", "SOFT", "SOFT", "SOFT", "SOFT", "SOFT", "SOFT", "SOFT", "SOFT", "SOFT", "SOFT", "SOFT", "SOFT"], "stint": [1, 1, 1, 1, 1, 1, 1, 1, 2, 2, 2, 3, 3, 3, 4, 4, 4], "s1": ["None", 26.288, 37.741, 36.871, 25.904, 47.182, 25.921, 32.225, "None", 25.519, 34.489, 78.868, 25.675, 32.571, "None", 26.939, 27.315], "s2": [53.102, 38.288, "None", 49.431, 38.694, "None", 38.816, 56.564, 53.046, 37.875, 58.313, 61.805, 38.619, 50.295, 46.288, 40.217, 47.096], "s3": [68.121, 32.896, "None", 52.773, 46.453, "None", 32.162, 37.372, 45.328, 31.48, 51.541, 49.848, 31.667, 40.923, 38.418, 33.207, 43.123], "life": [1, 2, 3, 4, 5, 6, 7, 8, 1, 2, 3, 4, 5, 6, 9, 10, 11], "pos": ["None", "None", "None", "None", "None", "None", "None", "None", "None", "None", "None", "None", "None", "None", "None", "None", "None"], "status": ["1", "1", "12", "1", "1", "1", "1", "1", "12", "1", "1", "1", "1", "1", "12", "12", "21"], "pb": [false, true, false, false, false, false, true, false, false, true, false, false, false, false, false, false, false]}