{"time": ["None", 79.725, 109.167, 79.366, 115.927, 79.069, 120.131, 79.025, 97.808, "None", 78.843, 114.423, 78.615, 89.925, "None", 77.555, 123.756, 132.57, 78.006, 99.437, 114.511], "lap": [1.0, 2.0, 3.0, 4.0, 5.0, 6.0, 7.0, 8.0, 9.0, 10.0, 11.0, 12.0, 13.0, 14.0, 15.0, 16.0, 17.0, 18.0, 19.0, 20.0, 21.0], "compound": ["HARD", "HARD", "HARD", "HARD", "HARD", "HARD", "HARD", "HARD", "HARD", "HARD", "HARD", "HARD", "HARD", "HARD", "SOFT", "SOFT", "SOFT", "SOFT", "SOFT", "SOFT", "SOFT"], "stint": [1, 1, 1, 1, 1, 1, 1, 1, 1, 2, 2, 2, 2, 2, 3, 3, 3, 4, 4, 4, 5], "s1": ["None", 28.596, 40.195, 28.75, 38.383, 28.659, 39.575, 28.682, 37.07, "None", 28.539, 41.995, 28.544, 30.614, "None", 28.111, 46.375, 66.89, 28.386, 32.753, 56.431], "s2": [33.585, 28.555, 43.067, 28.274, 48.936, 28.105, 50.728, 28.055, 33.625, 33.504, 28.068, 44.134, 27.974, 30.897, 43.141, 27.572, 44.896, 39.551, 27.772, 36.579, 30.529], "s3": [36.472, 22.574, 25.905, 22.342, 28.608, 22.305, 29.828, 22.288, 27.113, 24.783, 22.236, 28.294, 22.097, 28.414, 26.843, 21.872, 32.485, 26.129, 21.848, 30.105, 27.551], "life": [1, 2, 3, 4, 5, 6, 7, 8, 9, 10, 11, 12, 13, 14, 1, 2, 3, 1, 2, 3, 5], "pos": ["None", "None", "None", "None", "None", "None", "None", "None", "None", "None", "None", "None", "None", "None", "None", "None", "None", "None", "None", "None", "None"], "status": ["1", "1", "1", "1", "1", "1", "12", "12", "21", "1", "1", "1", "1", "1", "1", "1", "1", "1", "1", "1", "1"], "pb": [false, true, false, true, false, true, false, true, false, false, true, false, true, false, false, true, false, false, false, false, false]}