{"time": ["None", 65.752, 91.273, 66.064, 124.641, "None", 65.033, 89.778, "None", 64.942, 85.404, "None", 64.671, 90.296], "lap": [1.0, 2.0, 3.0, 4.0, 5.0, 6.0, 7.0, 8.0, 9.0, 10.0, 11.0, 12.0, 13.0, 14.0], "compound": ["SOFT", "SOFT", "SOFT", "SOFT", "SOFT", "SOFT", "SOFT", "SOFT", "SOFT", "SOFT", "SOFT", "SOFT", "SOFT", "SOFT"], "stint": [1, 1, 1, 1, 1, 2, 2, 2, 3, 3, 3, 4, 4, 4], "s1": ["None", 16.493, 19.96, 16.487, 18.853, "None", 16.432, 21.292, "None", 16.445, 18.849, "None", 16.308, 19.508], "s2": [38.048, 29.341, 42.617, 29.585, 39.009, 41.987, 29.039, 38.688, 33.855, 28.938, 33.814, 49.923, 28.849, 37.82], "s3": [26.166, 19.918, 28.696, 19.992, 66.779, 37.394, 19.562, 29.798, 24.492, 19.559, 32.741, 39.146, 19.514, 32.968], "life": [1, 2, 3, 4, 5, 1, 2, 3, 1, 2, 3, 1, 2, 3], "pos": ["None", "None", "None", "None", "None", "None", "None", "None", "None", "None", "None", "None", "None", "None"], "status": ["1", "1", "1", "1", "1", "1", "1", "1", "1", "1", "1", "1", "1", "1"], "pb": [false, true, false, false, false, false, true, false, false, true, false, false, true, false]}